fzfy/__init__.py
fzfy-0.0.2.dist-info/LICENSE
fzfy-0.0.2.dist-info/METADATA
fzfy-0.0.2.dist-info/WHEEL
fzfy-0.0.2.dist-info/top_level.txt
fzfy-0.0.2.dist-info/RECORD
