Metadata-Version: 2.1
Name: fzfy
Version: 0.0.2
Summary: A fzf wrapper
Author-email: Fernando Silveira <fsilveira@gmail.com>
Project-URL: Homepage, https://github.com/swrh/fzfy
Project-URL: Bug Tracker, https://github.com/swrh/fzfy/issues
Classifier: Programming Language :: Python :: 3
Classifier: License :: OSI Approved :: MIT License
Classifier: Operating System :: OS Independent
Requires-Python: >=3.7
License-File: LICENSE
